PythonBianchengShiguangFix1/README.md
PythonBianchengShiguangFix1/__init__.py
PythonBianchengShiguangFix1/__main__.py
PythonBianchengShiguangFix1/file.epub
PythonBianchengShiguangFix1/index.html
PythonBianchengShiguangFix1/css/__init__.py
PythonBianchengShiguangFix1/css/annotations.css
PythonBianchengShiguangFix1/css/main.css
PythonBianchengShiguangFix1/css/normalize.css
PythonBianchengShiguangFix1/css/popup.css
PythonBianchengShiguangFix1/font/__init__.py
PythonBianchengShiguangFix1/font/fontello.eot
PythonBianchengShiguangFix1/font/fontello.svg
PythonBianchengShiguangFix1/font/fontello.ttf
PythonBianchengShiguangFix1/font/fontello.woff
PythonBianchengShiguangFix1/img/__init__.py
PythonBianchengShiguangFix1/img/annotator-glyph-sprite.png
PythonBianchengShiguangFix1/img/annotator-icon-sprite.png
PythonBianchengShiguangFix1/img/apple-touch-icon.png
PythonBianchengShiguangFix1/img/cancelfullscreen.png
PythonBianchengShiguangFix1/img/close.png
PythonBianchengShiguangFix1/img/fullscreen.png
PythonBianchengShiguangFix1/img/loader.gif
PythonBianchengShiguangFix1/img/menu-icon.png
PythonBianchengShiguangFix1/img/save.png
PythonBianchengShiguangFix1/img/saved.png
PythonBianchengShiguangFix1/img/settings-s.png
PythonBianchengShiguangFix1/img/settings.png
PythonBianchengShiguangFix1/img/star.png
PythonBianchengShiguangFix1/js/__init__.py
PythonBianchengShiguangFix1/js/epub.js
PythonBianchengShiguangFix1/js/epub.min.js
PythonBianchengShiguangFix1/js/epub.min.map
PythonBianchengShiguangFix1/js/hooks.min.js
PythonBianchengShiguangFix1/js/hooks.min.map
PythonBianchengShiguangFix1/js/reader.js
PythonBianchengShiguangFix1/js/reader.js.map
PythonBianchengShiguangFix1/js/reader.min.js
PythonBianchengShiguangFix1/js/reader.min.map
PythonBianchengShiguangFix1/js/hooks/__init__.py
PythonBianchengShiguangFix1/js/hooks/extensions/__init__.py
PythonBianchengShiguangFix1/js/hooks/extensions/highlight.js
PythonBianchengShiguangFix1/js/libs/__init__.py
python_biancheng_shiguang_fix1-2025.3.25.0.dist-info/METADATA
python_biancheng_shiguang_fix1-2025.3.25.0.dist-info/WHEEL
python_biancheng_shiguang_fix1-2025.3.25.0.dist-info/entry_points.txt
python_biancheng_shiguang_fix1-2025.3.25.0.dist-info/top_level.txt
python_biancheng_shiguang_fix1-2025.3.25.0.dist-info/RECORD
